seedshield/__init__.py
seedshield/config.py
seedshield/display_handler.py
seedshield/input_handler.py
seedshield/main.py
seedshield/secure_memory.py
seedshield/secure_word_interface.py
seedshield/state_handler.py
seedshield/ui_manager.py
seedshield/data/english.txt
seedshield-0.2.2.dist-info/LICENSE
seedshield-0.2.2.dist-info/METADATA
seedshield-0.2.2.dist-info/WHEEL
seedshield-0.2.2.dist-info/entry_points.txt
seedshield-0.2.2.dist-info/top_level.txt
seedshield-0.2.2.dist-info/RECORD
