Metadata-Version: 2.2
Name: SeedShield
Version: 0.2.2
Summary: Secure BIP39 word viewer with masking and reveal functionality
Author-email: Barlog951 <barlog951@gmail.com>
Project-URL: Documentation, https://github.com/Barlog951/SeedShield/blob/main/README.md
Project-URL: Source Code, https://github.com/Barlog951/SeedShield
Project-URL: Bug Tracker, https://github.com/Barlog951/SeedShield/issues
Classifier: Development Status :: 3 - Alpha
Classifier: Environment :: Console
Classifier: Intended Audience :: End Users/Desktop
Classifier: License :: OSI Approved :: MIT License
Classifier: Operating System :: OS Independent
Classifier: Programming Language :: Python :: 3
Classifier: Programming Language :: Python :: 3.6
Classifier: Programming Language :: Python :: 3.7
Classifier: Programming Language :: Python :: 3.8
Classifier: Programming Language :: Python :: 3.9
Classifier: Programming Language :: Python :: 3.10
Classifier: Programming Language :: Python :: 3.11
Classifier: Programming Language :: Python :: 3.12
Classifier: Topic :: Security
Requires-Python: >=3.6
License-File: LICENSE
Requires-Dist: pyperclip>=1.8.0
Provides-Extra: test
Requires-Dist: pytest>=6.0; extra == "test"
Requires-Dist: pytest-timeout>=2.1.0; extra == "test"
Requires-Dist: pytest-cov; extra == "test"
Requires-Dist: pylint; extra == "test"
Requires-Dist: flake8; extra == "test"
Requires-Dist: mypy; extra == "test"
Provides-Extra: windows
Requires-Dist: windows-curses; extra == "windows"
Provides-Extra: dev
Requires-Dist: build; extra == "dev"
Requires-Dist: twine; extra == "dev"
